{"card_name": "Steelclade Herald", "color": "WU", "rarity": "rare", "type": "Artifact Creature \u2013 Construct Angel", "number": 122, "color_identity": "WU", "cost": "{2}{W}{U}{U}", "rules_text": "Inscribe\nFlying\nWhen Steelclade Herald enters the battlefield, put target artifact or enchantment card you own in exile onto the battlefield under your control.", "flavor_text": "[i][/i]", "pt": "5/4", "special_text": "", "shape": "normal", "set": "OZN", "loyalty": "", "artist": "wlop", "notes": "", "image_type": "png"}