{"card_name": "Divination Storm", "color": "UR", "rarity": "common", "type": "Instant", "number": 174, "color_identity": "UR", "cost": "{X}{1}{U}{R}", "rules_text": "The owner of target artifact or enchantment shuffles it into their library.\nScry X.\nFlashback {X}{3}{U}{R} [i](You may cast this card from your graveyard for its flashback cost. Then exile it.)[/i]", "flavor_text": "[i][/i]", "pt": "", "special_text": "", "shape": "normal", "set": "OZN", "loyalty": "", "artist": "gavinodonnell", "notes": "", "image_type": "png"}