{"card_name": "Beam of Life", "color": "G", "rarity": "common", "type": "Sorcery", "number": 125, "color_identity": "G", "cost": "{2}{G}", "rules_text": "Search your library for a basic land card or a stage land card, put it on the battlefield tapped, then shuffle.\nYou gain 1 life for each land that entered the battlefield this turn.", "flavor_text": "[i][/i]", "pt": "", "special_text": "", "shape": "normal", "set": "JLA", "loyalty": "", "artist": "Cobaltplasma", "notes": "", "image_type": "png"}