{"card_name": "Herald of Enervation", "color": "UR", "rarity": "uncommon", "type": "Creature \u2013 Angel Wizard", "number": 214, "color_identity": "UR", "cost": "{2}{U}{U}{R}", "rules_text": "Flying\n[i]Magecraft[/i] \u2013 Whenever you cast or copy an instant or sorcery spell, create a 1/1 blue Bird creature token with flying, it gains haste until end of turn.", "flavor_text": "[i][/i]", "pt": "3/3", "special_text": "", "shape": "normal", "set": "JLA", "loyalty": "", "artist": "JasonTN", "notes": "", "image_type": "png"}