{"card_name": "Kraken Grasping", "color": "UG", "rarity": "rare", "type": "Enchantment", "number": 35, "color_identity": "UG", "cost": "{1}{G}{U}", "rules_text": "[i]Lowtide [/i]\u2013 At the beginning of your end step, if you control three or less untapped Islands, create a tapped treasure token.\n[i]Hightide[/i] \u2013 At the beginning of your end step, if you control five or more untapped Islands, each opponent mills five cards.", "flavor_text": "[i][/i]", "pt": "", "special_text": "", "shape": "normal", "set": "YMD", "loyalty": "", "artist": "russelmarks", "notes": "", "image_type": "png"}