{"card_name": "Doom-Horn Reaver", "color": "WB", "rarity": "rare", "type": "Creature \u2013 Demon Minotaur", "number": 35, "color_identity": "WB", "cost": "{6}{W}{B}", "rules_text": "[i]Skullkeeping[/i] \u2013 When Doom-Horn Reaver enters the battlefield, each opponent loses life for each card you own in exile with a skull counter on it.\nCycling {3}{W}{B}\nWhenever you cycle Doom-Horn Reaver, each opponent loses 3 life.", "flavor_text": "[i][/i]", "pt": "7/7", "special_text": "", "shape": "normal", "set": "BMD", "loyalty": "", "artist": "yasenstoilov", "notes": "", "image_type": "png"}