{"card_name": "Angelic Ascension", "color": "WU", "rarity": "rare", "type": "Enchantment", "number": 11, "color_identity": "WU", "cost": "{3}{W}{W}{U}", "rules_text": "Whenever a card you own is put into exile from your graveyard or library, create a 4/4 white and blue angel with flying and prowess. This only triggers once each turn.\nIf you would draw a card except the first one you draw on each of your draw steps, you may exile the top card of your library instead. You may play that card until end of turn.", "flavor_text": "[i][/i]", "pt": "", "special_text": "", "shape": "normal", "set": "JLC", "loyalty": "", "artist": "JasonTN", "notes": "", "image_type": "png"}