{"card_name": "Scroll Snatcher", "color": "WU", "rarity": "uncommon", "type": "Creature \u2013 Human Wizard", "number": 224, "color_identity": "WU", "cost": "{W}{U}", "rules_text": "When Scroll Snatcher leaves the battlefield, exile target instant or sorcery card from an opponents graveyard. You may cast that card until the end of your next turn.\nRetreat 2 {4}{W}{U} [i](Exile this permanent face-down. Distribute up to two +1/+1 counters among up to two target creatures you control.)[/i]", "flavor_text": "[i][/i]", "pt": "1/1", "special_text": "", "shape": "normal", "set": "ASR", "loyalty": "", "artist": "Thaldir", "notes": "", "image_type": "png"}