{"card_name": "Herald of Memories", "color": "WG", "rarity": "rare", "type": "Creature \u2013 Angel Warrior", "number": 292, "color_identity": "WBG", "cost": "{4}{G}{W}", "rules_text": "Flying\nWhen Herald of Memories attacks, you may return target historic card from your graveyard to your hand.\nBlitz {2}{G}{W}", "flavor_text": "[i][/i]", "pt": "4/3", "special_text": "", "shape": "modal double faced", "set": "ASR", "loyalty": "", "artist": "shizen1102", "card_name2": "Uncover History", "color2": "WB", "type2": "Sorcery", "cost2": "{2}{W}{B}", "rules_text2": "Mill five cards, then return a historic card from your graveyard to your hand. [i](Artifacts, legendaries, and Sagas are historic.)[/i]\nEscape {1}{W}{B}, Exile four other cards from your graveyard.", "flavor_text2": "[i][/i]", "pt2": "", "special_text2": "", "loyalty2": "", "artist2": "edgarsh422", "notes": "", "image_type": "png"}