{"card_name": "Hexbreaker Gang", "color": "WG", "rarity": "rare", "type": "Creature \u2013 Human Artificer Warrior", "number": 293, "color_identity": "WUG", "cost": "{2}{G}{W}", "rules_text": "Improvise\nWard {3}\nRemove a counter from a permanent you control: You gain 1 life. Activate only as a sorcery.", "flavor_text": "[i][/i]", "pt": "3/4", "special_text": "", "shape": "modal double faced", "set": "ASR", "loyalty": "", "artist": "madspartan013", "card_name2": "Essence Weaver Elk", "color2": "UG", "type2": "Creature \u2013 Elk", "cost2": "{3}{G}{U}", "rules_text2": "Inscribe\nWhen Essence Weaver Elk enters, target permanent loses all its abilities and becomes a green Elk creature with base power and toughness 3/3 until Essence Weaver Elk leaves the battlefield.", "flavor_text2": "[i][/i]", "pt2": "4/4", "special_text2": "", "loyalty2": "", "artist2": "vasylina", "notes": "", "image_type": "png"}