{"card_name": "Seldanna, Timeless Diviner", "color": "W", "rarity": "rare", "type": "Legendary Creature \u2013 Elf Cleric Shaman", "number": 33, "color_identity": "W", "cost": "{3}{W}{W}", "rules_text": "Convoke [i](Your creatures can help cast this spell. Each creature you tap while casting this spell pays for {1} or one mana of that creature's color.)[/i]\nVigilance\nWhenever you cast your first artifact or enchantment spell each turn, create a 1/1 blue Bird creature token with flying, then populate. [i](Create a token that's a copy of a creature token you control.)[/i]", "flavor_text": "[i][/i]", "pt": "3/4", "special_text": "", "shape": "normal", "set": "ASR", "loyalty": "", "artist": "warmics", "notes": "", "image_type": "png"}