{"card_name": "Shadowrealm Slayer", "color": "BG", "rarity": "rare", "type": "Creature \u2013 Elf Rogue Warlock", "number": 356, "color_identity": "BRG", "cost": "{B}{G}", "rules_text": "Deathtouch\nWhenever a creature you don't control dies, exile it. \nWhenever one or more creature cards leave a players graveyard, draw a card. This ability only triggers once each turn.\n_", "flavor_text": "[i][/i]", "pt": "2/2", "special_text": "", "shape": "modal double faced", "set": "ASR", "loyalty": "", "artist": "chrisnazgul", "card_name2": "Uncontestable Challenge", "color2": "BR", "type2": "Instant", "cost2": "{X}{1}{B}{R}", "rules_text2": "Uncontestable Challenge deals X damage to up to three targets. If a permanent would be put into a graveyard this turn, exile it instead.", "flavor_text2": "[i][/i]", "pt2": "", "special_text2": "", "loyalty2": "", "artist2": "alaiaorx", "notes": "", "image_type": "png"}