{"card_name": "The Gothorn Project", "color": "UBG", "rarity": "rare", "type": "Legendary Enchantment \u2013 Saga", "number": 446, "color_identity": "UBG", "cost": "{2}{B}{G}{U}", "rules_text": "", "flavor_text": "[i][/i]", "pt": "", "special_text": "[i](As this Saga enters and after your draw step, add a lore counter. Sacrifice after III.)[/i]\nI \u2013 Exile target creature you control until The Gothorn Project leaves the battlefield.\nII \u2013 Creatures your opponents control get -1/-1 and lose all abilities until your next turn.\nIII \u2013 When a creature you control enters this turn, put a trample counter and two +1/+1 counters on it.", "shape": "saga", "set": "ASR", "loyalty": "", "artist": "domen_art", "notes": "", "image_type": "png"}