{"card_name": "Gothrian Charm", "color": "WUB", "rarity": "uncommon", "type": "Instant", "number": 447, "color_identity": "WUB", "cost": "{W}{U}{B}", "rules_text": "Choose one \u2013\n\u2022 Obscure the top two cards of your library [i](To obscure a card, exile it face down. You may play that card for as long as it remains exiled on a later turn.)[/i]\n\u2022 Target creature gets -1/-3 until end of turn.\n\u2022 Target noncreature artifact becomes a 3/3 construct creature in addition to its other types until end of turn.", "flavor_text": "[i][/i]", "pt": "", "special_text": "", "shape": "normal", "set": "ASR", "loyalty": "", "artist": "benlo", "notes": "", "image_type": "png"}