{"card_name": "Laci, Divine Gardener", "color": "WUG", "rarity": "uncommon", "type": "Legendary Creature \u2013 Human Angel Druid", "number": 462, "color_identity": "WUG", "cost": "{G}{W}{U}", "rules_text": "Flying\nWhenever you cast an artifact or enchantment spell, create a colorless Blossoming Field land token with \u201c{T}: Add one mana of any color among permanents you control.\u201d", "flavor_text": "[i][/i]", "pt": "2/4", "special_text": "", "shape": "normal", "set": "ASR", "loyalty": "", "artist": "yuumei", "notes": "", "image_type": "png"}