{"card_name": "Faeruson Manipulation", "color": "UBR", "rarity": "uncommon", "type": "Legendary Enchantment \u2013 Aura", "number": 595, "color_identity": "UBR", "cost": "{3}{UR}{BR}", "rules_text": "Enchant legendary permanent\nYou control enchanted permanent.\nAt the beginning of your end step, if you control a permanent you don't own, each opponent loses 2 life. You gain life equal to the amount of life lost this way.", "flavor_text": "[i][/i]", "pt": "", "special_text": "", "shape": "normal", "set": "ASR", "loyalty": "", "artist": "cobaltplasma", "notes": "", "image_type": "png"}