{"card_name": "Scaled Mercenary", "color": "URG", "rarity": "uncommon", "type": "Creature \u2013 Viashino Soldier", "number": 623, "color_identity": "URG", "cost": "{3}{R}{GU}", "rules_text": "[i]Formidable[/i] \u2013 {2}{R}: Scaled Mercenary deals 2 damage to target creature. Activate this only creatures you control have total power 8 or greater.\nEscape {2}{R}{R}, Exile two other cards from your graveyard.", "flavor_text": "[i][/i]", "pt": "3/3", "special_text": "", "shape": "adventure", "set": "ASR", "loyalty": "", "artist": "samsantala", "card_name2": "Take Quest", "color2": "UG", "type2": "Instant \u2013 Adventure", "cost2": "{G}{U}", "rules_text2": "Draw a card. You may put a land card from your hand onto the battlefield.", "flavor_text2": "[i][/i]", "pt2": "", "special_text2": "", "loyalty2": "", "artist2": "", "notes": "", "image_type": "png"}