{"card_name": "Auriclious, Leyline Collider", "color": "WUBRG", "rarity": "mythic", "type": "Legendary Artifact Creature \u2013 Dragon God", "number": 655, "color_identity": "WUBRG", "cost": "{10}", "rules_text": "Flying\nAuriclious, Leyline Collider is all colors.\nAuriclious, Leyline Collider costs {1} less to cast for each color among permanents you control.\nWhenever you cast a multicolored spell, add one mana of that spell's colors. Until end of turn, you don't lose this mana as steps and phases end. Use this mana only for multicolored spells.", "flavor_text": "[i][/i]", "pt": "8/8", "special_text": "", "shape": "normal", "set": "ASR", "loyalty": "", "artist": "Sandara", "notes": "", "image_type": "png"}