{"card_name": "Mangus, Gothorn Capital", "color": "", "rarity": "rare", "type": "Legendary Artifact Land \u2013 Capital", "number": 712, "color_identity": "UBG", "cost": "", "rules_text": "{T}: Add {B}.\n{B}, {T}: Add {B}{G}, {G}{U}, or {U}{B}.\n{B}{G}{U}, {T}: Target creature you control connives. [i](Draw a card, then discard a card. If you discarded a nonland card, put a +1/+1 counter on that creature.)[/i]", "flavor_text": "[i][/i]", "pt": "", "special_text": "", "shape": "normal", "set": "ASR", "loyalty": "", "artist": "insidegt", "notes": "", "image_type": "png"}