{"card_name": "Boglian Saleyard", "color": "B", "rarity": "common", "type": "Enchantment", "number": 88, "color_identity": "BG", "cost": "{1}{B}", "rules_text": "At the beginning of combat on your turn, you may sacrifice a historic permanent you control. If you do, put two +1/+1 counters onto target creature you control.", "flavor_text": "[i][/i]", "pt": "", "special_text": "", "shape": "adventure", "set": "ASR", "loyalty": "", "artist": "Hamsterfly", "card_name2": "Market Deal", "color2": "G", "type2": "Sorcery \u2013 Adventure", "cost2": "{2}{G}", "rules_text2": "Create two food tokens.", "flavor_text2": "[i][/i]", "pt2": "", "special_text2": "", "loyalty2": "", "artist2": "", "notes": "", "image_type": "png"}