{"card_name": "Fjorm, Princess of Ice", "color": "WUG", "rarity": "special", "type": "Legendary Snow Creature \u2013 Human Noble", "number": 1043, "color_identity": "WUG", "cost": "{G}{W}{U}", "rules_text": "[i]Nifl[/i] \u2013 Lands you control are Snow in addition to their other types.\n[i]Lieptr[/i] \u2013 Whenever a creature attacks you, if its tapped, put a stun counter on it.\n[i]Holy Vestments[/i] \u2013 Prevent all noncombat damage dealt to you and tapped creatures you control.", "flavor_text": "[i][/i]", "pt": "2/2", "special_text": "", "shape": "normal", "set": "FECM", "loyalty": "", "artist": "INTELLIGENT SYSTEMS", "notes": "", "image_type": "png"}