{"card_name": "The Immaculate One", "color": "WR", "rarity": "special", "type": "Legendary Creature \u2013 Demigod Dragon Shapeshifter", "number": 1167, "color_identity": "WR", "cost": "", "rules_text": "Flying, indestructible\n[i]Ancient Dragonskin[/i] \u2013 Dragons you control have absorb 5. [i](If a source would deal damage to this creature, prevent 5 of that damage.)[/i]\n[i]Giant Wings[/i] \u2013 Whenever another creature you control with flying attacks, they gain shroud until end of turn.\n[i]Wrath of Seiros[/i] \u2013 When The Immaculate One dies, each player sacrifices three lands they control.", "flavor_text": "[i][/i]", "pt": "8/8", "special_text": "", "shape": "normal", "set": "FECM", "loyalty": "", "artist": "INTELLIGENT SYSTEMS", "notes": "", "image_type": "png"}