{"card_name": "Lorenz, House Gloucester", "color": "BR", "rarity": "special", "type": "Legendary Creature \u2013 Human Knight Noble", "number": 1610, "color_identity": "BR", "cost": "{2}{B}{R}", "rules_text": "Menace\n[i]Distinguished House[/i] \u2013 If an opponent would lose life during your turn, that player loses that much life plus 2 instead.\n[i]Crest of Gloucester[/i] \u2013 Whenever you cast an instant or sorcery spell, target opponent chosen at random loses 2 life.\n[i]Promoted Class[/i] \u2013 {B}{R}", "flavor_text": "[i][/i]", "pt": "5/4", "special_text": "", "shape": "normal", "set": "FECM", "loyalty": "", "artist": "INTELLIGENT SYSTEMS", "notes": "", "image_type": "png"}