{"card_name": "Lyndis, Sacaen Survivor", "color": "WG", "rarity": "special", "type": "Legendary Creature \u2013 Human Nomad Lord Noble", "number": 1638, "color_identity": "WG", "cost": "{G}{W}", "rules_text": "Flash\n[i]Lorca Tribe Heir[/i] \u2013 As long as you control a Plains, Nomads you control have first strike.\n[i]Mani Katti[/i] \u2013 Whenever Lyndis, Sacaen Survivor deals combat damage to a creature, put a double strike counter onto a creature you control.", "flavor_text": "[i][/i]", "pt": "3/1", "special_text": "", "shape": "normal", "set": "FECM", "loyalty": "", "artist": "yagaminoue", "notes": "", "image_type": "png"}