{"card_name": "Shinon, Deadly Adept", "color": "BRG", "rarity": "special", "type": "Legendary Creature \u2013 Human Archer", "number": 1728, "color_identity": "BRG", "cost": "{2}{B}{R}{G}", "rules_text": "Deathtouch, reach, haste\n[i]Scavenger[/i] \u2013 When Shinon, Deadly Adept enters, draw three cards, then discard two cards, then Forge.\n[i]Deadly Adept[/i] \u2013 Equipped creatures you control have deathtouch.\n[i]Promote[/i] \u2013 At the beginning of your end step, if Shinon dealt 5 or more damage this turn, transform him.", "flavor_text": "[i][/i]", "pt": "3/5", "special_text": "", "shape": "normal", "set": "FECM", "loyalty": "", "artist": "INTELLIGENT SYSTEMS", "notes": "", "image_type": "png"}