{"card_name": "Sothis, Girl on the Throne", "color": "UBG", "rarity": "special", "type": "Legendary Creature \u2013 God", "number": 1787, "color_identity": "UBG", "cost": "{B}{G}{U}", "rules_text": "Indestructible\n[i]Alive Within Your Heart[/i] \u2013 Sothis can't attack or block.\n[i]Divine Pulse[/i] \u2013 {2}{B}{G}{U}: Target creature you control can't be blocked this turn. Prevent all damage that would be dealt to it this turn.", "flavor_text": "[i][/i]", "pt": "3/3", "special_text": "", "shape": "normal", "set": "FECM", "loyalty": "", "artist": "INTELLIGENT SYSTEMS", "notes": "", "image_type": "png"}