{"card_name": "Sylvain of House Gautier", "color": "WR", "rarity": "special", "type": "Legendary Creature \u2013 Human Knight Noble", "number": 1815, "color_identity": "WR", "cost": "{3}{R}{W}", "rules_text": "Trample\n[i]Flourishing Love[/i] \u2013 Whenever you cast a creature spell with partner with, forge.\n[i]Crest of Gautier[/i] \u2013 Whenever you cast a spell that targets a creature, Sylvain, House Gautier, gets +2/+2 until end of turn.\n[i]Promoted Class[/i] \u2013 {1}{W}{R} [i](You may put this card over another Sylvain creature you own. They mutate into the creature on top plus all abilities from under it.)[/i]", "flavor_text": "[i][/i]", "pt": "5/4", "special_text": "", "shape": "normal", "set": "FECM", "loyalty": "", "artist": "nanbuyasu", "notes": "", "image_type": "png"}