{"card_name": "Virion, Elite Archer", "color": "WU", "rarity": "special", "type": "Legendary Creature \u2013 Human Archer Noble", "number": 1896, "color_identity": "WU", "cost": "{1}{W}{U}", "rules_text": "Reach\n[i]Prescience[/i] \u2013 When Virion, Elite Archer or another Archer you control enters, look at the top two cards of your library. Put one of the cards into your hand and the other on the bottom of your library.\n[i]Promote[/i] \u2013 When Virion deals damage to a creature with flying, transform him.", "flavor_text": "[i][/i]", "pt": "1/4", "special_text": "", "shape": "normal", "set": "FECM", "loyalty": "", "artist": "Kotaro Yamada", "notes": "", "image_type": "png"}