{"card_name": "Warrior's Might", "color": "WR", "rarity": "special", "type": "Enchantment \u2013 Aura", "number": 1900, "color_identity": "WR", "cost": "{R}{W}", "rules_text": "Enchant creature\nEnchanted creature gets +1/+1 and has trample.\n[i]Crit[/i] \u2013 Whenever enchanted creature deals combat damage to a player, you may create a copy of Warrior's Might.", "flavor_text": "[i][/i]", "pt": "", "special_text": "", "shape": "normal", "set": "FECM", "loyalty": "", "artist": "INTELLIGENT SYSTEMS", "notes": "", "image_type": "png"}