{"card_name": "Triandra, Sunlit Nightmare", "color": "UBR", "rarity": "special", "type": "Legendary Creature \u2013 Elf Faerie Nightmare", "number": 2088, "color_identity": "UBR", "cost": "{1}{U}{B}{R}", "rules_text": "Flying, ward {1}\n[i]Nightmares[/i] \u2013 At the beginning of each opponents upkeep, that player mills two cards.\n[i]Rude Awakening[/i] \u2013 Whenever a creature an opponent controls untaps, Triandra, Blissful Fright deals 1 damage to that creatures controller.", "flavor_text": "[i][/i]", "pt": "3/3", "special_text": "", "shape": "normal", "set": "FECM", "loyalty": "", "artist": "INTELLIGENT SYSTEMS", "notes": "", "image_type": "png"}