{"card_name": "Manster", "color": "", "rarity": "special", "type": "Legendary Land \u2013 Island", "number": 2232, "color_identity": "U", "cost": "", "rules_text": "[i]({T}: Add {U}.)[/i]\n[i]Cleared[/i] \u2013 At the beginning of your end step, if you attacked a player with exactly two creatures this turn, put a cleared counter on this land. As long as it has a cleared counter on it, it has \u201c{T}: Add one mana of any color.", "flavor_text": "[i][/i]", "pt": "", "special_text": "", "shape": "normal", "set": "FECM", "loyalty": "", "artist": "Fenori", "notes": "", "image_type": "png"}