{"card_name": "Cordelia, Heartstrung Bride", "color": "W", "rarity": "special", "type": "Legendary Creature \u2013 Human", "number": 612, "color_identity": "W", "cost": "{3}{W}", "rules_text": "Reach\n[i]True Love[/i] \u2013 When Cordelia enters, create a Lover Role token, and attach it to a creature you control . [i](If you control another Role on it, put that one into the graveyard. Enchanted creature gets +1/+1 and has \u201cWhenever enchanted creature attacks, you gain 1 life\u201d.)[/i]\n[i]Unbreakable Bond[/i] \u2013 Enchanted creatures you control get +0/+2.\n[i]Pair Up[/i] \u2013 Whenever Cordelia attacks a player, if exactly one other creature is attacking that player, create a Lover Role token, and attach it to a creature you control.", "flavor_text": "[i][/i]", "pt": "3/4", "special_text": "", "shape": "normal", "set": "FECM", "loyalty": "", "artist": "INTELLIGENT SYSTEMS", "notes": "", "image_type": "png"}