{"card_name": "Alcryst's Fortified Shot", "color": "UR", "rarity": "special", "type": "Legendary Instant", "number": 616, "color_identity": "UR", "cost": "{U}{R}", "rules_text": "Alcryst's Fortified Shot deals X damage to target creature, where X is the greatest toughness among creatures you control.\nYou may exchange the power and toughness of up to two target creatures until end of turn.", "flavor_text": "[i][/i]", "pt": "", "special_text": "", "shape": "normal", "set": "FECM", "loyalty": "", "artist": "INTELLIGENT SYSTEMS", "notes": "", "image_type": "png"}